fnplus/__init__.py
fnplus/curried.py
fnplus/either.py
fnplus/iterable.py
fnplus/monad.py
fnplus-0.4.1.dist-info/DESCRIPTION.rst
fnplus-0.4.1.dist-info/METADATA
fnplus-0.4.1.dist-info/RECORD
fnplus-0.4.1.dist-info/WHEEL
fnplus-0.4.1.dist-info/metadata.json
fnplus-0.4.1.dist-info/top_level.txt
