Metadata-Version: 2.0
Name: fnplus
Version: 0.4.1
Summary: Yet another functional programming library
Home-page: http://github.com/mdowds/fnplus
Author: Matt Dowds
Author-email: UNKNOWN
License: MIT
Platform: UNKNOWN
